odoo9_addon_account_financial_report_horizontal-9.0.0.0.0-py2.7-nspkg.pth
odoo_addons/account_financial_report_horizontal/__openerp__.py
odoo_addons/account_financial_report_horizontal/__init__.py
odoo_addons/account_financial_report_horizontal/README.rst
odoo_addons/account_financial_report_horizontal/report/report_financial.xml
odoo_addons/account_financial_report_horizontal/report/report_financial.py
odoo_addons/account_financial_report_horizontal/report/__init__.py
odoo_addons/account_financial_report_horizontal/models/account_financial_report.py
odoo_addons/account_financial_report_horizontal/models/__init__.py
odoo_addons/account_financial_report_horizontal/data/ir_actions_report_xml.xml
odoo_addons/account_financial_report_horizontal/data/report_paperformat.xml
odoo_addons/account_financial_report_horizontal/tests/__init__.py
odoo_addons/account_financial_report_horizontal/tests/test_account_financial_report_horizontal.py
odoo_addons/account_financial_report_horizontal/static/description/icon.png
odoo9_addon_account_financial_report_horizontal-9.0.0.0.0.dist-info/top_level.txt
odoo9_addon_account_financial_report_horizontal-9.0.0.0.0.dist-info/WHEEL
odoo9_addon_account_financial_report_horizontal-9.0.0.0.0.dist-info/RECORD
odoo9_addon_account_financial_report_horizontal-9.0.0.0.0.dist-info/metadata.json
odoo9_addon_account_financial_report_horizontal-9.0.0.0.0.dist-info/DESCRIPTION.rst
odoo9_addon_account_financial_report_horizontal-9.0.0.0.0.dist-info/METADATA
odoo9_addon_account_financial_report_horizontal-9.0.0.0.0.dist-info/namespace_packages.txt
