Metadata-Version: 2.0
Name: odoo9-addon-account-financial-report-horizontal
Version: 9.0.0.0.0
Summary: Accounting Financial Reports Horizontal
Home-page: https://github.com/OCA/account-financial-reporting
Author: UNKNOWN
Author-email: UNKNOWN
License: AGPL-3
Platform: UNKNOWN
Requires-Dist: odoo (<9.1a,>=9.0a)
Classifier: Programming Language :: Python :: 2.7
Classifier: Framework :: Odoo
Classifier: License :: OSI Approved :: GNU Affero General Public License v3
